{
	"info": {
		"_postman_id": "0e90a3db-2f8c-400c-92eb-e35341fa1f64",
		"name": "post_man-Collections",
		"schema": "https://schema.getpostman.com/json/collection/v2.1.0/collection.json",
		"_exporter_id": "31096711"
	},
	"item": [
		{
			"name": "create conversation",
			"request": {
				"method": "POST",
				"header": [],
				"url": {
					"raw": "localhost:8000/coverstions/create/",
					"host": [
						"localhost"
					],
					"port": "8000",
					"path": [
						"coverstions",
						"create",
						""
					]
				}
			},
			"response": []
		}
	]
}